quoll/__init__.py
quoll/frc/__init__.py
quoll/frc/frc_calibration_functions.py
quoll/frc/oneimg.py
quoll/io/__init__.py
quoll/io/mdoc_parser.py
quoll/io/reader.py
quoll/io/tiles.py
quoll/ui/__init__.py
quoll/ui/frc_oneimg_ui.py
quoll-0.0.4.dist-info/LICENSE
quoll-0.0.4.dist-info/METADATA
quoll-0.0.4.dist-info/WHEEL
quoll-0.0.4.dist-info/entry_points.txt
quoll-0.0.4.dist-info/top_level.txt
quoll-0.0.4.dist-info/RECORD
