Metadata-Version: 2.1
Name: quoll
Version: 0.0.4
Summary: Image quality assessment for electron tomography
Author-email: Elaine Ho <elaine.ho@rfi.ac.uk>
License: Apache License
Project-URL: Homepage, https://github.com/rosalindfranklininstitute/quoll
Project-URL: Bug Tracker, https://github.com/rosalindfranklininstitute/quoll/issues
Classifier: Programming Language :: Python :: 3
Classifier: License :: OSI Approved :: Apache Software License
Classifier: Operating System :: OS Independent
Requires-Python: >=3.6
License-File: LICENSE
Requires-Dist: matplotlib
Requires-Dist: quoll-compatible-miplib
Requires-Dist: mrcfile
Requires-Dist: notebook
Requires-Dist: numpy
Requires-Dist: pandas
Requires-Dist: scikit-image
Requires-Dist: scipy
Requires-Dist: tifffile
Requires-Dist: tqdm
